mcp_server_docy/__init__.py
mcp_server_docy/__main__.py
mcp_server_docy/server.py
mcp_server_docy-0.5.0.dist-info/METADATA
mcp_server_docy-0.5.0.dist-info/WHEEL
mcp_server_docy-0.5.0.dist-info/entry_points.txt
mcp_server_docy-0.5.0.dist-info/licenses/LICENSE
mcp_server_docy-0.5.0.dist-info/RECORD
