Metadata-Version: 2.4
Name: mcp-server-docy
Version: 0.5.0
Summary: A Model Context Protocol (MCP) server for accessing documentation
Author: Oliver Borchers
License: MIT
License-File: LICENSE
Keywords: automation,documentation,llm,mcp,scraper
Classifier: Development Status :: 4 - Beta
Classifier: Intended Audience :: Developers
Classifier: License :: OSI Approved :: MIT License
Classifier: Programming Language :: Python :: 3
Classifier: Programming Language :: Python :: 3.11
Requires-Python: >=3.11
Requires-Dist: crawl4ai>=0.6.0rc1
Requires-Dist: diskcache>=5.6.1
Requires-Dist: fastmcp>=2.2.2
Requires-Dist: loguru>=0.7.3
Requires-Dist: pydantic-settings>=2.0.0
Requires-Dist: pydantic>=2.0.0
